plotfig/__init__.py
plotfig/brain_connection.py
plotfig/brain_surface.py
plotfig/circos.py
plotfig/correlation.py
plotfig/matrix.py
plotfig/multi_bars.py
plotfig/single_bar.py
plotfig/data/atlas_tables/chimpanzee_bna.csv
plotfig/data/atlas_tables/human_bna.csv
plotfig/data/atlas_tables/human_glasser.csv
plotfig/data/atlas_tables/macaque_bna.csv
plotfig/data/atlas_tables/macaque_charm4.csv
plotfig/data/atlas_tables/macaque_charm5.csv
plotfig/data/atlas_tables/macaque_charm5_add_13_sgms.csv
plotfig/data/atlas_tables/macaque_charm6.csv
plotfig/data/atlas_tables/macaque_d99.csv
plotfig/data/neurodata/atlases/chimpanzee_BNA/ChimpBNA.L.32k_fs_LR.label.gii
plotfig/data/neurodata/atlases/chimpanzee_BNA/ChimpBNA.R.32k_fs_LR.label.gii
plotfig/data/neurodata/atlases/human_BNA/fsaverage.L.BNA.32k_fs_LR.label.gii
plotfig/data/neurodata/atlases/human_BNA/fsaverage.R.BNA.32k_fs_LR.label.gii
plotfig/data/neurodata/atlases/human_Glasser/fsaverage.L.Glasser.32k_fs_LR.label.gii
plotfig/data/neurodata/atlases/human_Glasser/fsaverage.R.Glasser.32k_fs_LR.label.gii
plotfig/data/neurodata/atlases/macaque_BNA/MBNA_124_32k_L.label.gii
plotfig/data/neurodata/atlases/macaque_BNA/MBNA_124_32k_R.label.gii
plotfig/data/neurodata/atlases/macaque_CHARM4/L.charm4.label.gii
plotfig/data/neurodata/atlases/macaque_CHARM4/R.charm4.label.gii
plotfig/data/neurodata/atlases/macaque_CHARM5/L.charm5.label.gii
plotfig/data/neurodata/atlases/macaque_CHARM5/R.charm5.label.gii
plotfig/data/neurodata/atlases/macaque_CHARM6/L.charm6.label.gii
plotfig/data/neurodata/atlases/macaque_CHARM6/R.charm6.label.gii
plotfig/data/neurodata/atlases/macaque_D99/L.d99.label.gii
plotfig/data/neurodata/atlases/macaque_D99/R.d99.label.gii
plotfig/data/neurodata/surfaces/chimpanzee_BNA/ChimpYerkes29_v1.2.L.midthickness.32k_fs_LR.surf.gii
plotfig/data/neurodata/surfaces/chimpanzee_BNA/ChimpYerkes29_v1.2.L.veryinflated.32k_fs_LR.surf.gii
plotfig-1.15.0.dist-info/METADATA
plotfig-1.15.0.dist-info/WHEEL
plotfig-1.15.0.dist-info/licenses/LICENSE
plotfig-1.15.0.dist-info/RECORD
