Metadata-Version: 2.4
Name: plotfig
Version: 1.15.0
Summary: Scientific plotting package for Cognitive neuroscience
Author-email: Ricardo Ryn <ricardoRyn1317@gmail.com>
License-File: LICENSE
Keywords: neuroscience,plotting,visualization
Requires-Python: >=3.11
Requires-Dist: brainspace>=0.1.22
Requires-Dist: imageio>=2.37.2
Requires-Dist: kaleido>=1.0.0
Requires-Dist: loguru>=0.7.3
Requires-Dist: matplotlib>=3.10.6
Requires-Dist: nibabel>=5.3.2
Requires-Dist: numpy>=2.3.2
Requires-Dist: plotly>=6.3.0
Requires-Dist: pycirclize>=1.10.0
Requires-Dist: scipy>=1.16.1
Requires-Dist: tqdm>=4.67.1
